codefly_cli/__init__.py
codefly_cli/buf/validate/expression_pb2.py
codefly_cli/buf/validate/expression_pb2_grpc.py
codefly_cli/buf/validate/priv/private_pb2.py
codefly_cli/buf/validate/priv/private_pb2_grpc.py
codefly_cli/buf/validate/validate_pb2.py
codefly_cli/buf/validate/validate_pb2_grpc.py
codefly_cli/ci.py
codefly_cli/codefly/__init__.py
codefly_cli/codefly/actions/v0/module_pb2.py
codefly_cli/codefly/actions/v0/module_pb2_grpc.py
codefly_cli/codefly/actions/v0/organization_pb2.py
codefly_cli/codefly/actions/v0/organization_pb2_grpc.py
codefly_cli/codefly/actions/v0/service_pb2.py
codefly_cli/codefly/actions/v0/service_pb2_grpc.py
codefly_cli/codefly/actions/v0/workspace_pb2.py
codefly_cli/codefly/actions/v0/workspace_pb2_grpc.py
codefly_cli/codefly/base/v0/agent_pb2.py
codefly_cli/codefly/base/v0/agent_pb2_grpc.py
codefly_cli/codefly/base/v0/configuration_pb2.py
codefly_cli/codefly/base/v0/configuration_pb2_grpc.py
codefly_cli/codefly/base/v0/endpoint_pb2.py
codefly_cli/codefly/base/v0/endpoint_pb2_grpc.py
codefly_cli/codefly/base/v0/environment_pb2.py
codefly_cli/codefly/base/v0/environment_pb2_grpc.py
codefly_cli/codefly/base/v0/module_pb2.py
codefly_cli/codefly/base/v0/module_pb2_grpc.py
codefly_cli/codefly/base/v0/network_pb2.py
codefly_cli/codefly/base/v0/network_pb2_grpc.py
codefly_cli/codefly/base/v0/organization_pb2.py
codefly_cli/codefly/base/v0/organization_pb2_grpc.py
codefly_cli/codefly/base/v0/scope_pb2.py
codefly_cli/codefly/base/v0/scope_pb2_grpc.py
codefly_cli/codefly/base/v0/service_pb2.py
codefly_cli/codefly/base/v0/service_pb2_grpc.py
codefly_cli/codefly/base/v0/spec_pb2.py
codefly_cli/codefly/base/v0/spec_pb2_grpc.py
codefly_cli/codefly/base/v0/workspace_pb2.py
codefly_cli/codefly/base/v0/workspace_pb2_grpc.py
codefly_cli/codefly/cli/v0/cli_pb2.py
codefly_cli/codefly/cli/v0/cli_pb2_grpc.py
codefly_cli/codefly/observability/v0/dependencies_pb2.py
codefly_cli/codefly/observability/v0/dependencies_pb2_grpc.py
codefly_cli-0.0.19.dist-info/METADATA
codefly_cli-0.0.19.dist-info/WHEEL
codefly_cli-0.0.19.dist-info/RECORD
