Metadata-Version: 2.1
Name: codefly-cli
Version: 0.0.19
Summary: 
Author: Antoine Toussaint
Author-email: antoine.toussaint@codefly.ai
Requires-Python: >=3.10,<4.0
Classifier: Programming Language :: Python :: 3
Classifier: Programming Language :: Python :: 3.10
Classifier: Programming Language :: Python :: 3.11
Classifier: Programming Language :: Python :: 3.12
Requires-Dist: PyYAML (>=6.0.1,<7.0.0)
Requires-Dist: codefly-sdk (>=0.0.14,<0.0.15)
Requires-Dist: grpcio (>=1.63.0,<2.0.0)
Requires-Dist: grpclib (>=0.4.7,<0.5.0)
Requires-Dist: protobuf (>=5.26.1,<6.0.0)
Requires-Dist: pydantic (>=2.7.1,<3.0.0)
Requires-Dist: pytest (>=8.2.0,<9.0.0)
